{
    "10.999195337295573": {
        "10.999210121215828": {
            "counter": 1,
            "normal": "C:\\Users\\Johannes\\Dropbox\\Uni\\CSE\\Year 2\\Quarter 4\\Software Project\\Programming\\TestClone\\mesh-city\\src\\mesh_city\\resources\\images\\request_3\\0_tile_0_0\\concat_image_request_10_tile_0_0.png"
        },
        "11.0": {
            "counter": 4,
            "normal": "C:\\Users\\Johannes\\Dropbox\\Uni\\CSE\\Year 2\\Quarter 4\\Software Project\\Programming\\TestClone\\mesh-city\\src\\mesh_city\\resources\\images\\request_3\\0_tile_0_0\\concat_image_request_10_tile_0_0.png"
        },
        "11.000789878784172": {
            "counter": 7,
            "normal": "C:\\Users\\Johannes\\Dropbox\\Uni\\CSE\\Year 2\\Quarter 4\\Software Project\\Programming\\TestClone\\mesh-city\\src\\mesh_city\\resources\\images\\request_3\\0_tile_0_0\\concat_image_request_10_tile_0_0.png"
        }
    },
    "11.0": {
        "10.999210121215828": {
            "counter": 2,
            "normal": "C:\\Users\\Johannes\\Dropbox\\Uni\\CSE\\Year 2\\Quarter 4\\Software Project\\Programming\\TestClone\\mesh-city\\src\\mesh_city\\resources\\images\\request_3\\0_tile_0_0\\concat_image_request_10_tile_0_0.png"
        },
        "11.0": {
            "counter": 5,
            "normal": "C:\\Users\\Johannes\\Dropbox\\Uni\\CSE\\Year 2\\Quarter 4\\Software Project\\Programming\\TestClone\\mesh-city\\src\\mesh_city\\resources\\images\\request_3\\0_tile_0_0\\concat_image_request_10_tile_0_0.png"
        },
        "11.000789878784172": {
            "counter": 8,
            "normal": "C:\\Users\\Johannes\\Dropbox\\Uni\\CSE\\Year 2\\Quarter 4\\Software Project\\Programming\\TestClone\\mesh-city\\src\\mesh_city\\resources\\images\\request_3\\0_tile_0_0\\concat_image_request_10_tile_0_0.png"
        }
    },
    "11.000804662704427": {
        "10.999210121215828": {
            "counter": 3,
            "normal": "C:\\Users\\Johannes\\Dropbox\\Uni\\CSE\\Year 2\\Quarter 4\\Software Project\\Programming\\TestClone\\mesh-city\\src\\mesh_city\\resources\\images\\request_3\\0_tile_0_0\\concat_image_request_10_tile_0_0.png"
        },
        "11.0": {
            "counter": 6,
            "normal": "C:\\Users\\Johannes\\Dropbox\\Uni\\CSE\\Year 2\\Quarter 4\\Software Project\\Programming\\TestClone\\mesh-city\\src\\mesh_city\\resources\\images\\request_3\\0_tile_0_0\\concat_image_request_10_tile_0_0.png"
        },
        "11.000789878784172": {
            "counter": 9,
            "normal": "C:\\Users\\Johannes\\Dropbox\\Uni\\CSE\\Year 2\\Quarter 4\\Software Project\\Programming\\TestClone\\mesh-city\\src\\mesh_city\\resources\\images\\request_3\\0_tile_0_0\\concat_image_request_10_tile_0_0.png"
        }
    },
    "11.000402331352213": {
        "11.000394939392086": {
            "counter": 1,
            "normal": "C:\\Users\\Johannes\\Dropbox\\Uni\\CSE\\Year 2\\Quarter 4\\Software Project\\Programming\\TestClone\\mesh-city\\src\\mesh_city\\resources\\images\\request_149\\0_tile_0_0\\concat_image_request_10_tile_0_0.png"
        },
        "11.00118481711791": {
            "counter": 4,
            "normal": "C:\\Users\\Johannes\\Dropbox\\Uni\\CSE\\Year 2\\Quarter 4\\Software Project\\Programming\\TestClone\\mesh-city\\src\\mesh_city\\resources\\images\\request_149\\0_tile_0_0\\concat_image_request_10_tile_0_0.png"
        },
        "11.001974692726929": {
            "counter": 7,
            "normal": "C:\\Users\\Johannes\\Dropbox\\Uni\\CSE\\Year 2\\Quarter 4\\Software Project\\Programming\\TestClone\\mesh-city\\src\\mesh_city\\resources\\images\\request_149\\0_tile_0_0\\concat_image_request_10_tile_0_0.png"
        },
        "11.002764566219": {
            "counter": 1,
            "normal": "C:\\Users\\Johannes\\Dropbox\\Uni\\CSE\\Year 2\\Quarter 4\\Software Project\\Programming\\TestClone\\mesh-city\\src\\mesh_city\\resources\\images\\request_149\\2_tile_0_1\\concat_image_request_10_tile_0_1.png"
        },
        "11.003554437593976": {
            "counter": 4,
            "normal": "C:\\Users\\Johannes\\Dropbox\\Uni\\CSE\\Year 2\\Quarter 4\\Software Project\\Programming\\TestClone\\mesh-city\\src\\mesh_city\\resources\\images\\request_149\\2_tile_0_1\\concat_image_request_10_tile_0_1.png"
        },
        "11.004344306851715": {
            "counter": 7,
            "normal": "C:\\Users\\Johannes\\Dropbox\\Uni\\CSE\\Year 2\\Quarter 4\\Software Project\\Programming\\TestClone\\mesh-city\\src\\mesh_city\\resources\\images\\request_149\\2_tile_0_1\\concat_image_request_10_tile_0_1.png"
        }
    },
    "11.00120699405664": {
        "11.000394939392086": {
            "counter": 2,
            "normal": "C:\\Users\\Johannes\\Dropbox\\Uni\\CSE\\Year 2\\Quarter 4\\Software Project\\Programming\\TestClone\\mesh-city\\src\\mesh_city\\resources\\images\\request_149\\0_tile_0_0\\concat_image_request_10_tile_0_0.png"
        },
        "11.00118481711791": {
            "counter": 5,
            "normal": "C:\\Users\\Johannes\\Dropbox\\Uni\\CSE\\Year 2\\Quarter 4\\Software Project\\Programming\\TestClone\\mesh-city\\src\\mesh_city\\resources\\images\\request_149\\0_tile_0_0\\concat_image_request_10_tile_0_0.png"
        },
        "11.001974692726929": {
            "counter": 8,
            "normal": "C:\\Users\\Johannes\\Dropbox\\Uni\\CSE\\Year 2\\Quarter 4\\Software Project\\Programming\\TestClone\\mesh-city\\src\\mesh_city\\resources\\images\\request_149\\0_tile_0_0\\concat_image_request_10_tile_0_0.png"
        },
        "11.002764566219": {
            "counter": 2,
            "normal": "C:\\Users\\Johannes\\Dropbox\\Uni\\CSE\\Year 2\\Quarter 4\\Software Project\\Programming\\TestClone\\mesh-city\\src\\mesh_city\\resources\\images\\request_149\\2_tile_0_1\\concat_image_request_10_tile_0_1.png"
        },
        "11.003554437593976": {
            "counter": 5,
            "normal": "C:\\Users\\Johannes\\Dropbox\\Uni\\CSE\\Year 2\\Quarter 4\\Software Project\\Programming\\TestClone\\mesh-city\\src\\mesh_city\\resources\\images\\request_149\\2_tile_0_1\\concat_image_request_10_tile_0_1.png"
        },
        "11.004344306851715": {
            "counter": 8,
            "normal": "C:\\Users\\Johannes\\Dropbox\\Uni\\CSE\\Year 2\\Quarter 4\\Software Project\\Programming\\TestClone\\mesh-city\\src\\mesh_city\\resources\\images\\request_149\\2_tile_0_1\\concat_image_request_10_tile_0_1.png"
        }
    },
    "11.002011656761066": {
        "11.000394939392086": {
            "counter": 3,
            "normal": "C:\\Users\\Johannes\\Dropbox\\Uni\\CSE\\Year 2\\Quarter 4\\Software Project\\Programming\\TestClone\\mesh-city\\src\\mesh_city\\resources\\images\\request_149\\0_tile_0_0\\concat_image_request_10_tile_0_0.png"
        },
        "11.00118481711791": {
            "counter": 6,
            "normal": "C:\\Users\\Johannes\\Dropbox\\Uni\\CSE\\Year 2\\Quarter 4\\Software Project\\Programming\\TestClone\\mesh-city\\src\\mesh_city\\resources\\images\\request_149\\0_tile_0_0\\concat_image_request_10_tile_0_0.png"
        },
        "11.001974692726929": {
            "counter": 9,
            "normal": "C:\\Users\\Johannes\\Dropbox\\Uni\\CSE\\Year 2\\Quarter 4\\Software Project\\Programming\\TestClone\\mesh-city\\src\\mesh_city\\resources\\images\\request_149\\0_tile_0_0\\concat_image_request_10_tile_0_0.png"
        },
        "11.002764566219": {
            "counter": 3,
            "normal": "C:\\Users\\Johannes\\Dropbox\\Uni\\CSE\\Year 2\\Quarter 4\\Software Project\\Programming\\TestClone\\mesh-city\\src\\mesh_city\\resources\\images\\request_149\\2_tile_0_1\\concat_image_request_10_tile_0_1.png"
        },
        "11.003554437593976": {
            "counter": 6,
            "normal": "C:\\Users\\Johannes\\Dropbox\\Uni\\CSE\\Year 2\\Quarter 4\\Software Project\\Programming\\TestClone\\mesh-city\\src\\mesh_city\\resources\\images\\request_149\\2_tile_0_1\\concat_image_request_10_tile_0_1.png"
        },
        "11.004344306851715": {
            "counter": 9,
            "normal": "C:\\Users\\Johannes\\Dropbox\\Uni\\CSE\\Year 2\\Quarter 4\\Software Project\\Programming\\TestClone\\mesh-city\\src\\mesh_city\\resources\\images\\request_149\\2_tile_0_1\\concat_image_request_10_tile_0_1.png"
        }
    },
    "11.002816319465493": {
        "11.000394939392086": {
            "counter": 1,
            "normal": "C:\\Users\\Johannes\\Dropbox\\Uni\\CSE\\Year 2\\Quarter 4\\Software Project\\Programming\\TestClone\\mesh-city\\src\\mesh_city\\resources\\images\\request_149\\1_tile_1_0\\concat_image_request_10_tile_1_0.png"
        },
        "11.00118481711791": {
            "counter": 4,
            "normal": "C:\\Users\\Johannes\\Dropbox\\Uni\\CSE\\Year 2\\Quarter 4\\Software Project\\Programming\\TestClone\\mesh-city\\src\\mesh_city\\resources\\images\\request_149\\1_tile_1_0\\concat_image_request_10_tile_1_0.png"
        },
        "11.001974692726929": {
            "counter": 7,
            "normal": "C:\\Users\\Johannes\\Dropbox\\Uni\\CSE\\Year 2\\Quarter 4\\Software Project\\Programming\\TestClone\\mesh-city\\src\\mesh_city\\resources\\images\\request_149\\1_tile_1_0\\concat_image_request_10_tile_1_0.png"
        },
        "11.002764566219": {
            "counter": 1,
            "normal": "C:\\Users\\Johannes\\Dropbox\\Uni\\CSE\\Year 2\\Quarter 4\\Software Project\\Programming\\TestClone\\mesh-city\\src\\mesh_city\\resources\\images\\request_149\\3_tile_1_1\\concat_image_request_10_tile_1_1.png"
        },
        "11.003554437593976": {
            "counter": 4,
            "normal": "C:\\Users\\Johannes\\Dropbox\\Uni\\CSE\\Year 2\\Quarter 4\\Software Project\\Programming\\TestClone\\mesh-city\\src\\mesh_city\\resources\\images\\request_149\\3_tile_1_1\\concat_image_request_10_tile_1_1.png"
        },
        "11.004344306851715": {
            "counter": 7,
            "normal": "C:\\Users\\Johannes\\Dropbox\\Uni\\CSE\\Year 2\\Quarter 4\\Software Project\\Programming\\TestClone\\mesh-city\\src\\mesh_city\\resources\\images\\request_149\\3_tile_1_1\\concat_image_request_10_tile_1_1.png"
        }
    },
    "11.00362098216992": {
        "11.000394939392086": {
            "counter": 2,
            "normal": "C:\\Users\\Johannes\\Dropbox\\Uni\\CSE\\Year 2\\Quarter 4\\Software Project\\Programming\\TestClone\\mesh-city\\src\\mesh_city\\resources\\images\\request_149\\1_tile_1_0\\concat_image_request_10_tile_1_0.png"
        },
        "11.00118481711791": {
            "counter": 5,
            "normal": "C:\\Users\\Johannes\\Dropbox\\Uni\\CSE\\Year 2\\Quarter 4\\Software Project\\Programming\\TestClone\\mesh-city\\src\\mesh_city\\resources\\images\\request_149\\1_tile_1_0\\concat_image_request_10_tile_1_0.png"
        },
        "11.001974692726929": {
            "counter": 8,
            "normal": "C:\\Users\\Johannes\\Dropbox\\Uni\\CSE\\Year 2\\Quarter 4\\Software Project\\Programming\\TestClone\\mesh-city\\src\\mesh_city\\resources\\images\\request_149\\1_tile_1_0\\concat_image_request_10_tile_1_0.png"
        },
        "11.002764566219": {
            "counter": 2,
            "normal": "C:\\Users\\Johannes\\Dropbox\\Uni\\CSE\\Year 2\\Quarter 4\\Software Project\\Programming\\TestClone\\mesh-city\\src\\mesh_city\\resources\\images\\request_149\\3_tile_1_1\\concat_image_request_10_tile_1_1.png"
        },
        "11.003554437593976": {
            "counter": 5,
            "normal": "C:\\Users\\Johannes\\Dropbox\\Uni\\CSE\\Year 2\\Quarter 4\\Software Project\\Programming\\TestClone\\mesh-city\\src\\mesh_city\\resources\\images\\request_149\\3_tile_1_1\\concat_image_request_10_tile_1_1.png"
        },
        "11.004344306851715": {
            "counter": 8,
            "normal": "C:\\Users\\Johannes\\Dropbox\\Uni\\CSE\\Year 2\\Quarter 4\\Software Project\\Programming\\TestClone\\mesh-city\\src\\mesh_city\\resources\\images\\request_149\\3_tile_1_1\\concat_image_request_10_tile_1_1.png"
        }
    },
    "11.004425644874347": {
        "11.000394939392086": {
            "counter": 3,
            "normal": "C:\\Users\\Johannes\\Dropbox\\Uni\\CSE\\Year 2\\Quarter 4\\Software Project\\Programming\\TestClone\\mesh-city\\src\\mesh_city\\resources\\images\\request_149\\1_tile_1_0\\concat_image_request_10_tile_1_0.png"
        },
        "11.00118481711791": {
            "counter": 6,
            "normal": "C:\\Users\\Johannes\\Dropbox\\Uni\\CSE\\Year 2\\Quarter 4\\Software Project\\Programming\\TestClone\\mesh-city\\src\\mesh_city\\resources\\images\\request_149\\1_tile_1_0\\concat_image_request_10_tile_1_0.png"
        },
        "11.001974692726929": {
            "counter": 9,
            "normal": "C:\\Users\\Johannes\\Dropbox\\Uni\\CSE\\Year 2\\Quarter 4\\Software Project\\Programming\\TestClone\\mesh-city\\src\\mesh_city\\resources\\images\\request_149\\1_tile_1_0\\concat_image_request_10_tile_1_0.png"
        },
        "11.002764566219": {
            "counter": 3,
            "normal": "C:\\Users\\Johannes\\Dropbox\\Uni\\CSE\\Year 2\\Quarter 4\\Software Project\\Programming\\TestClone\\mesh-city\\src\\mesh_city\\resources\\images\\request_149\\3_tile_1_1\\concat_image_request_10_tile_1_1.png"
        },
        "11.003554437593976": {
            "counter": 6,
            "normal": "C:\\Users\\Johannes\\Dropbox\\Uni\\CSE\\Year 2\\Quarter 4\\Software Project\\Programming\\TestClone\\mesh-city\\src\\mesh_city\\resources\\images\\request_149\\3_tile_1_1\\concat_image_request_10_tile_1_1.png"
        },
        "11.004344306851715": {
            "counter": 9,
            "normal": "C:\\Users\\Johannes\\Dropbox\\Uni\\CSE\\Year 2\\Quarter 4\\Software Project\\Programming\\TestClone\\mesh-city\\src\\mesh_city\\resources\\images\\request_149\\3_tile_1_1\\concat_image_request_10_tile_1_1.png"
        }
    }
}